valtra/__init__.py
valtra/dataloader.py
valtra/utils.py
valtra-0.1.0.dist-info/LICENSE
valtra-0.1.0.dist-info/METADATA
valtra-0.1.0.dist-info/WHEEL
valtra-0.1.0.dist-info/top_level.txt
valtra-0.1.0.dist-info/RECORD
