Metadata-Version: 2.2
Name: valtra
Version: 0.1.0
Summary: A dynamic dataset loader for PyTorch.
Home-page: https://github.com/marcosousapoza/valtra
Author: Marco Sousa-Poza
Author-email: Marco Sousa-Poza <marco.sousapoza@gmail.com>
Project-URL: Homepage, https://github.com/marcosousapoza/valtra
Requires-Python: >=3.7
License-File: LICENSE
Requires-Dist: torch
Dynamic: author
Dynamic: home-page
Dynamic: requires-python
